<?xml version="1.0" encoding="utf-8"?>
<CodecsInfo version="1.0.0.1">

  <!------ Video/Audio Effect ------>
  <codecs
    enable="0" priority="10"
    name="VsFilter"
    pathflag="file" 
    path="vsfilter.dll"
    category="dsfilter"
    type="veffect"
    clsid="{93A22E7A-5091-45EF-BA61-6DA26156A5D0}">
    <mediatype major="MEDIATYPE_Video" sub="MEDIASUBTYPE_YUY2"/>
    <mediatype major="MEDIATYPE_Video" sub="MEDIASUBTYPE_YV12"/>
    <mediatype major="MEDIATYPE_Video" sub="MEDIASUBTYPE_I420"/>
    <mediatype major="MEDIATYPE_Video" sub="MEDIASUBTYPE_IYUV"/>
    <mediatype major="MEDIATYPE_Video" sub="MEDIASUBTYPE_RGB32"/>
    <mediatype major="MEDIATYPE_Video" sub="MEDIASUBTYPE_RGB565"/>
    <mediatype major="MEDIATYPE_Video" sub="MEDIASUBTYPE_RGB555"/>
    <mediatype major="MEDIATYPE_Video" sub="MEDIASUBTYPE_RGB24"/>
    <mediatype major="MEDIATYPE_Text"  sub="MEDIASUBTYPE_None"/>
  </codecs>

  <codecs
    enable="1" priority="10"
    name="AudioSwitcher"
    pathflag="file"
    path="audioswitcher.ax"
    category="dsfilter"
    type="aeffect"
    preload="1"
    clsid="{18C16B08-6497-420E-AD14-22D21C2CEAB7}" >
    <mediatype major="MEDIATYPE_Audio" sub="GUID_NULL" />
  </codecs>

  <!------ Video/Audio Renderers ------>
  <!--VMR7-->
  <codecs
    enable="1" priority="8"
    name="Video Mixing Render 7"
    pathflag="reg"
    category="dsfilter"
    type="vrender"
    clsid="{B87BEB7B-8D29-423f-AE4D-6582C10175AC}" >
    <mediatype major="MEDIATYPE_Video" sub="MEDIASUBTYPE_YV12" />
    <mediatype major="MEDIATYPE_Video" sub="MEDIASUBTYPE_I420" />
    <mediatype major="MEDIATYPE_Video" sub="MEDIASUBTYPE_IYUV" />
    <mediatype major="MEDIATYPE_Video" sub="MEDIASUBTYPE_YUY2" />
    <mediatype major="MEDIATYPE_Video" sub="MEDIASUBTYPE_ARGB32" />
    <mediatype major="MEDIATYPE_Video" sub="MEDIASUBTYPE_RGB32" />
    <mediatype major="MEDIATYPE_Video" sub="MEDIASUBTYPE_RGB24" />
    <mediatype major="MEDIATYPE_Video" sub="MEDIASUBTYPE_RGB565" />
    <mediatype major="MEDIATYPE_Video" sub="MEDIASUBTYPE_RGB555" />
    <mediatype major="MEDIATYPE_Video" sub="DXVA_ModeMPEG2_D" />
    <mediatype major="MEDIATYPE_Video" sub="DXVA_ModeMPEG2_B" />
    <mediatype major="MEDIATYPE_Video" sub="DXVA_ModeMPEG2_C" />
    <mediatype major="MEDIATYPE_Video" sub="DXVA_ModeMPEG2_A" />
    <mediatype major="MEDIATYPE_Video" sub="DXVA_ModeMPEG2_D" />
    <mediatype major="MEDIATYPE_Video" sub="DXVA_ModeMPEG2_B" />
    <mediatype major="MEDIATYPE_Video" sub="DXVA_ModeMPEG2_C" />
    <mediatype major="MEDIATYPE_Video" sub="DXVA_ModeMPEG2_A" />
    <mediatype major="MEDIATYPE_Video" sub="GUID_NULL" />
  </codecs>

  <!--VMR9-->
  <codecs
    enable="1" priority="9"
    name="Video Mixing Render 9"
    pathflag="reg"
    category="dsfilter"
    type="vrender"
    clsid="{51B4ABF3-748F-4E3B-A276-C828330E926A}" >
    <mediatype major="MEDIATYPE_Video" sub="MEDIASUBTYPE_YV12" />
    <mediatype major="MEDIATYPE_Video" sub="MEDIASUBTYPE_I420" />
    <mediatype major="MEDIATYPE_Video" sub="MEDIASUBTYPE_IYUV" />
    <mediatype major="MEDIATYPE_Video" sub="MEDIASUBTYPE_YUY2" />
    <mediatype major="MEDIATYPE_Video" sub="MEDIASUBTYPE_ARGB32" />
    <mediatype major="MEDIATYPE_Video" sub="MEDIASUBTYPE_RGB32" />
    <mediatype major="MEDIATYPE_Video" sub="MEDIASUBTYPE_RGB24" />
    <mediatype major="MEDIATYPE_Video" sub="MEDIASUBTYPE_RGB565" />
    <mediatype major="MEDIATYPE_Video" sub="MEDIASUBTYPE_RGB555" />
    <mediatype major="MEDIATYPE_Video" sub="GUID_NULL" />
  </codecs>

  <!--EVR-->
  <codecs
    enable="1" priority="10"
    name="Enhanced Video Renderer"
    pathflag="reg"
    category="dsfilter"
    type="vrender"
    clsid="{FA10746C-9B63-4B6C-BC49-FC300EA5F256}" >
    <mediatype major="MEDIATYPE_Video" sub="MEDIASUBTYPE_YV12" />
    <mediatype major="MEDIATYPE_Video" sub="MEDIASUBTYPE_I420" />
    <mediatype major="MEDIATYPE_Video" sub="MEDIASUBTYPE_IYUV" />
    <mediatype major="MEDIATYPE_Video" sub="MEDIASUBTYPE_YUY2" />
    <mediatype major="MEDIATYPE_Video" sub="MEDIASUBTYPE_ARGB32" />
    <mediatype major="MEDIATYPE_Video" sub="MEDIASUBTYPE_RGB32" />
    <mediatype major="MEDIATYPE_Video" sub="MEDIASUBTYPE_RGB24" />
    <mediatype major="MEDIATYPE_Video" sub="MEDIASUBTYPE_RGB565" />
    <mediatype major="MEDIATYPE_Video" sub="MEDIASUBTYPE_RGB555" />
    <mediatype major="MEDIATYPE_Video" sub="MEDIASUBTYPE_NV12" />
    <mediatype major="MEDIATYPE_Video" sub="GUID_NULL" />
  </codecs>


  <!--EVRCP-->
  <codecs
    enable="1" priority="11"
    name="NTPlayer EVRCP"
    pathflag="inner"
    category="dsfilter"
    type="vrender"
    clsid="{7612b889-e070-4bcc-b808-91cb794174ab}" >
    <mediatype major="MEDIATYPE_Video" sub="MEDIASUBTYPE_YV12" />
    <mediatype major="MEDIATYPE_Video" sub="MEDIASUBTYPE_I420" />
    <mediatype major="MEDIATYPE_Video" sub="MEDIASUBTYPE_IYUV" />
    <mediatype major="MEDIATYPE_Video" sub="MEDIASUBTYPE_YUY2" />
    <mediatype major="MEDIATYPE_Video" sub="MEDIASUBTYPE_ARGB32" />
    <mediatype major="MEDIATYPE_Video" sub="MEDIASUBTYPE_RGB32" />
    <mediatype major="MEDIATYPE_Video" sub="MEDIASUBTYPE_RGB24" />
    <mediatype major="MEDIATYPE_Video" sub="MEDIASUBTYPE_RGB565" />
    <mediatype major="MEDIATYPE_Video" sub="MEDIASUBTYPE_RGB555" />
    <mediatype major="MEDIATYPE_Video" sub="MEDIASUBTYPE_NV12" />
    <mediatype major="MEDIATYPE_Video" sub="GUID_NULL" />
  </codecs>

  <codecs
    enable="1" priority="7"
    name="Video Render Default"
    pathflag="reg"
    category="dsfilter"
    type="vrender"
    clsid="{6BC1CFFA-8FC1-4261-AC22-CFB4CC38DB50}" >
    <mediatype major="MEDIATYPE_Video" sub="MEDIASUBTYPE_YV12" />
    <mediatype major="MEDIATYPE_Video" sub="MEDIASUBTYPE_I420" />
    <mediatype major="MEDIATYPE_Video" sub="MEDIASUBTYPE_IYUV" />
    <mediatype major="MEDIATYPE_Video" sub="MEDIASUBTYPE_YUY2" />
    <mediatype major="MEDIATYPE_Video" sub="MEDIASUBTYPE_ARGB32" />
    <mediatype major="MEDIATYPE_Video" sub="MEDIASUBTYPE_RGB32" />
    <mediatype major="MEDIATYPE_Video" sub="MEDIASUBTYPE_RGB24" />
    <mediatype major="MEDIATYPE_Video" sub="MEDIASUBTYPE_RGB565" />
    <mediatype major="MEDIATYPE_Video" sub="MEDIASUBTYPE_RGB555" />
    <mediatype major="MEDIATYPE_Video" sub="DXVA_ModeMPEG2_A" />
    <mediatype major="MEDIATYPE_Video" sub="DXVA_ModeMPEG2_B" />
    <mediatype major="MEDIATYPE_Video" sub="DXVA_ModeMPEG2_C" />
    <mediatype major="MEDIATYPE_Video" sub="DXVA_ModeMPEG2_D" />
    <mediatype major="MEDIATYPE_Video"  sub="GUID_NULL" />
  </codecs>
  
  <!--Old Renderer-->
  <codecs
    enable="1" priority="6"
    name="Video Renderer (Old)"
    pathflag="reg"
    category="dsfilter"
    type="vrender"
    clsid="{70E102B0-5556-11CE-97C0-00AA0055595A}" >
    <mediatype major="MEDIATYPE_Video" sub="GUID_NULL" />
  </codecs>

  <!--Audio Renderer-->
  <codecs
    enable="1" priority="10"
    name="Default DirectSound Device"
    pathflag="reg"
    category="dsfilter"
    type="arender"
    clsid="{79376820-07D0-11CF-A24D-0020AFD79767}" >
    <mediatype major="MEDIATYPE_Audio" sub="MEDIASUBTYPE_PCM" />
    <mediatype major="MEDIATYPE_Audio" sub="MEDIASUBTYPE_DRM_Audio" />
    <mediatype major="MEDIATYPE_Audio" sub="MEDIASUBTYPE_IEEE_FLOAT" />
    <mediatype major="MEDIATYPE_Audio" sub="MEDIASUBTYPE_DOLBY_AC3_SPDIF" />
    <mediatype major="MEDIATYPE_Audio" sub="MEDIASUBTYPE_RAW_SPORT" />
    <mediatype major="MEDIATYPE_Audio" sub="MEDIASUBTYPE_SPDIF_TAG_241h" />
    <mediatype major="MEDIATYPE_Audio" sub="MEDIASUBTYPE_WMASPDIF" />
    <!--mediatype major="MEDIATYPE_Audio" sub="{00000249-0000-0010-8000-00aa00389b71}" /-->
    <mediatype major="MEDIATYPE_Audio" sub="GUID_NULL" />
  </codecs>

  <codecs
    enable="1" priority="10"
    name="NullTextRenderer"
    pathflag="inner"
    category="dsfilter"
    type="nullrender"
    clsid="{655D7613-C26C-4A25-BBBD-3C9C516122CC}" >
    <mediatype major="MEDIATYPE_Text" sub="GUID_NULL" />
    <mediatype major="MEDIATYPE_ScriptCommand" sub="GUID_NULL" />
    <mediatype major="MEDIATYPE_Subtitle" sub="GUID_NULL" />
  </codecs>

  <!------ Source Filters ------>
  <codecs
    enable="1" priority="10"
    name="PlayerAsyncReader"
    pathflag="inner"
    category="dsfilter"
    type="src"
    clsid="{2E03B28F-EA09-464e-9EDA-52FF59C13E13}" >
    <!--rmvb-->
    <checkbyte value="0,4,,2E524D46|MEDIASUBTYPE_RealMedia" />
    <!--mkv-->
    <checkbyte value="0,4,,1A45DFA3|MEDIASUBTYPE_Matroska" />
    <!--avi-->
    <checkbyte value="0,4,,52494646,8,4,,41564919|MEDIASUBTYPE_Avi" />
    <checkbyte value="0,4,,52494646,8,4,,41564920|MEDIASUBTYPE_Avi" />
    <checkbyte value="0,4,,52494646,8,4,,41564958|MEDIASUBTYPE_Avi" />
    <checkbyte value="0,4,,52494646,8,4,,414D5620|MEDIASUBTYPE_Avi" />
    <!--wmv-->
    <!--checkbyte value="0,16,,3026B2758E66CF11A6D900AA0062CE6C|{6B6D0801-9ADA-11D0-A520-00A0D10129C0}" /-->

    <!--mov/mp4 -->
    <checkbyte value="4,4,,66747970|MEDIASUBTYPE_MP4" />
    <checkbyte value="4,4,,6d6f6f76|MEDIASUBTYPE_MP4" />
    <checkbyte value="4,4,,6d646174|MEDIASUBTYPE_MP4" />
    <checkbyte value="4,4,,736b6970|MEDIASUBTYPE_MP4" />
    <checkbyte value="4,12,ffffffff00000000ffffffff,77696465000000006d646174|MEDIASUBTYPE_MP4" />
    <checkbyte value="3,3,,000001|MEDIASUBTYPE_MP4" />
    <checkbyte value="4,4,,706e6f74|MEDIASUBTYPE_MP4" />

    <!--mpeg-->
    <!--checkbyte value="0,2,,FFFB|{ABCDEF00-0000-0000-0000-000000000001}" />
    <checkbyte value="0,2,,FFF9|{ABCDEF00-0000-0000-0000-000000000003}" />
    <checkbyte value="0,2,,FFFA|{ABCDEF00-0000-0000-0000-000000000004}" /-->
    <checkbyte value="0,2,,FFFD|MEDIASUBTYPE_MPEG1Audio" />
    <checkbyte value="0,10,FFFFFF00000080808080,49443300000000000000|MEDIASUBTYPE_MPEG1Audio" />
    <checkbyte value="0,16,FFFFFFFFF100010001800001FFFFFFFF,000001BA2100010001800001000001BB|MEDIASUBTYPE_MPEG2_TRANSPORT" />
    <checkbyte value="0,5,FFFFFFFFC0,000001BA40|MEDIASUBTYPE_MPEG2_TRANSPORT" />
    <checkbyte value="0,1,,47,188,1,,47,376,1,,47|MEDIASUBTYPE_MPEG2_TRANSPORT" />
    <checkbyte value="4,1,,47,196,1,,47,388,1,,47|MEDIASUBTYPE_MPEG2_TRANSPORT" />
    <checkbyte value="0,4,,54467263,1660,1,,47|MEDIASUBTYPE_MPEG2_TRANSPORT" />
    <checkbyte value="0,8,fffffc00ffe00000,4156000055000000|MEDIASUBTYPE_MPEG2_TRANSPORT" />

    <!--flv-->
    <checkbyte value="0,4,ffffff00,43575300|MEDIASUBTYPE_FLV" />
    <checkbyte value="0,4,ffffff00,46575300|MEDIASUBTYPE_FLV" />
    <checkbyte value="0,4,ffffff00,464C5600|MEDIASUBTYPE_FLV" />
    <checkbyte value="0,4,,464C5601|MEDIASUBTYPE_FLV" />

    <protocol value="file"/>
    <protocol value="qvod"/>
  </codecs>
  
  <codecs
    enable="1" priority="10"
    name="File Source (Async.)"
    pathflag="reg"
    category="dsfilter"
    type="src"
    clsid="{E436EBB5-524F-11CE-9F53-0020AF0BA770}" >
    <!--rmvb-->
    <checkbyte value="0,4,,2E524D46|MEDIASUBTYPE_RealMedia" />
    <!--mkv-->
    <checkbyte value="0,4,,1A45DFA3|MEDIASUBTYPE_Matroska" />
    <!--avi-->
    <checkbyte value="0,4,,52494646,8,4,,41564919|MEDIASUBTYPE_Avi" />
    <checkbyte value="0,4,,52494646,8,4,,41564920|MEDIASUBTYPE_Avi" />
    <checkbyte value="0,4,,52494646,8,4,,41564958|MEDIASUBTYPE_Avi" />
    <checkbyte value="0,4,,52494646,8,4,,414D5620|MEDIASUBTYPE_Avi" />
    <!--wmv-->
    <!--checkbyte value="0,16,,3026B2758E66CF11A6D900AA0062CE6C|{6B6D0801-9ADA-11D0-A520-00A0D10129C0}" /-->

    <!--mov/mp4 -->
    <checkbyte value="4,4,,66747970|MEDIASUBTYPE_MP4" />
    <checkbyte value="4,4,,6d6f6f76|MEDIASUBTYPE_MP4" />
    <checkbyte value="4,4,,6d646174|MEDIASUBTYPE_MP4" />
    <checkbyte value="4,4,,736b6970|MEDIASUBTYPE_MP4" />
    <checkbyte value="4,12,ffffffff00000000ffffffff,77696465000000006d646174|MEDIASUBTYPE_MP4" />
    <checkbyte value="3,3,,000001|MEDIASUBTYPE_MP4" />
    <checkbyte value="4,4,,706e6f74|MEDIASUBTYPE_MP4" />

    <!--mpeg-->
    <!--checkbyte value="0,2,,FFFB|{ABCDEF00-0000-0000-0000-000000000001}" />
    <checkbyte value="0,2,,FFF9|{ABCDEF00-0000-0000-0000-000000000003}" />
    <checkbyte value="0,2,,FFFA|{ABCDEF00-0000-0000-0000-000000000004}" /-->
    <checkbyte value="0,2,,FFFD|MEDIASUBTYPE_MPEG1Audio" />
    <checkbyte value="0,10,FFFFFF00000080808080,49443300000000000000|MEDIASUBTYPE_MPEG1Audio" />
    <checkbyte value="0,16,FFFFFFFFF100010001800001FFFFFFFF,000001BA2100010001800001000001BB|MEDIASUBTYPE_MPEG2_TRANSPORT" />
    <checkbyte value="0,5,FFFFFFFFC0,000001BA40|MEDIASUBTYPE_MPEG2_TRANSPORT" />
    <checkbyte value="0,1,,47,188,1,,47,376,1,,47|MEDIASUBTYPE_MPEG2_TRANSPORT" />
    <checkbyte value="4,1,,47,196,1,,47,388,1,,47|MEDIASUBTYPE_MPEG2_TRANSPORT" />
    <checkbyte value="0,4,,54467263,1660,1,,47|MEDIASUBTYPE_MPEG2_TRANSPORT" />
    <checkbyte value="0,8,fffffc00ffe00000,4156000055000000|MEDIASUBTYPE_MPEG2_TRANSPORT" />

    <!--flv-->
    <checkbyte value="0,4,ffffff00,43575300|MEDIASUBTYPE_FLV" />
    <checkbyte value="0,4,ffffff00,46575300|MEDIASUBTYPE_FLV" />
    <checkbyte value="0,4,ffffff00,464C5600|MEDIASUBTYPE_FLV" />
    <checkbyte value="0,4,,464C5601|MEDIASUBTYPE_FLV" />

    <protocol value="file"/>
  </codecs>

  <codecs
    enable="1" priority="10"
    name="AC3File"
    pathflag="file"
    path="ac3file.dll"
    category="dsfilter"
    type="src"
    clsid="{F7380D4C-DE45-4F03-9209-15EBA8552463}" >
    <protocol value="file" />
    <!--WAV-->
    <checkbyte value="0,4,,52494646,8,4,,57415645" />
    <!--AC3-->
    <checkbyte value="0,4,,7FFE8001" />
    <checkbyte value="0,2,,0B77" />
    <checkbyte value="0,2,,770B" />
  </codecs>

  <codecs
    enable="1" priority="10"
    name="WM ASF Reader"
    pathflag="file"
    path="qasf.dll"
    category="dsfilter"
    type="src"
    clsid="{187463A0-5BB7-11D3-ACBE-0080C75E246E}" >
    <protocol value="file" />
    <checkbyte value="0,16,,3026B2758E66CF11A6D900AA0062CE6C" />
    <checkbyte value="0,10,FFFFFF00000080808080,49443300000000000000" />
    <ext value=".wmv" />
    <ext value=".wma" />
    <ext value=".asf" />
  </codecs>

  <codecs
    enable="1" priority="10"
    name="WMSF (Implement with WmvCore Not DRMStub)"
    pathflag="file"
    path="wmsf.ax"
    category="dsfilter"
    type="src"
    clsid="{85F61D5F-7DD5-5d6d-BFFC-F6D75F699C38}" >
    <protocol value="file"/>
    <checkbyte value="0,16,,3026B2758E66CF11A6D900AA0062CE6C"/>
    <checkbyte value="0,10,FFFFFF00000080808080,49443300000000000000"/>
  </codecs>

  <codecs
    enable="1" priority="10"
    name="WM ASF Reader (only for RTSP)"
    pathflag="file"
    path="qasf.dll"
    category="dsfilter"
    type="src"
    clsid="{187463A0-5BB7-11D3-ACBE-0080C75E246E}" >
    <protocol value="rtsp" />
  </codecs>

  <codecs
    enable="1" priority="10"
    name="Haali Media Source"
    pathflag="file"
    path="splitter.ax"
    category="dsfilter"
    type="src"
    clsid="{55DA30FC-F16B-49FC-BAA5-AE59FC65F82D}" >
    <protocol value="file"/>
    <checkbyte value="0,4,,4F676753" />
    <depend dll="mkx.dll" />
    <depend dll="ogm.dll" />
    <ext value=".ogg" />
  </codecs>

  <codecs
    enable="1" priority="10"
    name="Haali Media Splitter"
    pathflag="file"
    path="splitter.ax"
    category="dsfilter"
    type="src"
    clsid="{55DA30FC-F16B-49FC-BAA5-AE59FC65F82D}" >
    <protocol value="file"/>
    <!-- dependence -->
    <depend dll="avi.dll" />
    <depend dll="mkx.dll" />
    <depend dll="mp4.dll" />
    <depend dll="ogm.dll" />
    <depend dll="ts.dll" />
    <!-- AVI container -->
    <checkbyte value="0,4,,52494646,8,4,,41564920" />
    <checkbyte value="0,4,,52494646,8,4,,41564958" />
    <!-- Mpeg container -->
    <!-- <checkbyte value="116,1,,47,304,1,,47,492,1,,47" /> -->
    <!-- <checkbyte value="128,1,,47,316,1,,47,504,1,,47" /> -->
    <checkbyte value="0,16,FFFFFFFFF100010001800001FFFFFFFF,000001BA2100010001800001000001BB" />
    <checkbyte value="0,4,,54467263,1660,1,,47" />
    <checkbyte value="0,8,fffffc00ffe00000,4156000055000000" />
    <checkbyte value="0,5,FFFFFFFFC0,000001BA40" />
    <!-- MP4 container -->
    <checkbyte value="4,4,,66747970" />
    <checkbyte value="4,4,,6d6f6f76" />
    <checkbyte value="4,4,,6d646174" />
    <checkbyte value="4,4,,736b6970" />
    <checkbyte value="4,12,ffffffff00000000ffffffff,77696465027fe3706d646174" />
    <checkbyte value="3,3,,000001" />
    <checkbyte value="4,4,,66747970,527,4,,736F7774" />
    <checkbyte value="4,8,,667479706D703432,16,8,,6D70343269736F6D" />
    <checkbyte value="0,5,FFFFFFFFC0,000001BA40" />
    <!-- MKV container -->
    <checkbyte value="0,4,,1A45DFA3" />
  </codecs>


  <codecs
    enable="1" priority="10"
    name="Haali Media Splitter"
    pathflag="file"
    path="splitter.ax"
    category="dsfilter"
    type="src"
    clsid="{55DA30FC-F16B-49FC-BAA5-AE59FC65F82D}" >
    <protocol value="file"/>
    <depend dll="mkx.dll" />
    <depend dll="ts.dll" />
    <!-- Mpeg container -->
    <ext value=".evo" />
    <checkbyte value="0,1,,47,188,1,,47,376,1,,47|MEDIASUBTYPE_MPEG2_TRANSPORT" />
    <checkbyte value="4,1,,47,196,1,,47,388,1,,47|MEDIASUBTYPE_MPEG2_TRANSPORT" />
  </codecs>

  <codecs
    enable="1" priority="10"
    name="Nero Digital Parser"
    pathflag="file"
    path="ndparser.ax"
    category="dsfilter"
    type="src"
    clsid="{E206E4DE-A7EE-4A62-B3E9-4FBC8FE84C73}" >
    <protocol value="file"/>
    <checkbyte value="4,4,,66747970"/>
    <checkbyte value="4,4,,6d6f6f76"/>
    <checkbyte value="4,4,,6d646174"/>
    <checkbyte value="4,4,,736b6970"/>
    <checkbyte value="4,12,ffffffff00000000ffffffff,77696465000000006d646174"/>
    <checkbyte value="3,3,,000001"/>
  </codecs>

  <!--codecs
    enable="1" priority="10"
    name="Matroska Source"
    pathflag="file"
    path="matroskasplitter.ax"
    category="dsfilter"
    type="src"
    clsid="{0A68C3B5-9164-4A54-AFAF-995B2FF0E0D4}" >
    <protocol value="file"/>
    <ext value=".mkv"/>
    <checkbyte value="0,4,,1A45DFA3|MEDIASUBTYPE_Matroska"/>
  </codecs-->

  <codecs
    enable="1" priority="10"
    name="Mpa Source"
    pathflag="file"
    path="mpasplitter.ax"
    category="dsfilter"
    type="src"
    clsid="{59A0DB73-0287-4C9A-9D3C-8CFF39F8E5DB}" >
    <checkbyte value="0,2,FFE0,FFE0"/>
  </codecs>

  <codecs
    enable="1" priority="10"
    name="DC_Bass Source"
    pathflag="file"
    path="dcbasssource.ax"
    category="dsfilter"
    type="src"
    clsid="{ABE7B1D9-4B3E-4ACD-A0D1-92611D3A4492}" >
    <protocol value="file"/>
    <checkbyte value="0,4,,664c6143" />
    <checkbyte value="0,4,,4d414320" />
    <checkbyte value="0,4,,7776706b" />
    <checkbyte value="0,4,,4D50434B" />
    <checkbyte value="0,3,,4D502B" />
    <checkbyte value="0,4,,54544131" />
    <checkbyte value="0,4,,52494646,8,4,,57415645" />
    <checkbyte value="0,10,FFFFFF00000080808080,49443300000000000000" />
    <checkbyte value="0,2,FFE0,FFE0" />
    <checkbyte value="0,16,,00000000000000000000000000000000" />
    <checkbyte value="4,8,,667479704D344120" />
    <checkbyte value="0,4,,464f524d,8,4,,41494646" />
    <checkbyte value="0,4,,464f524d,8,4,,41494643" />
    <ext value=".mp3" />
    <ext value=".ape" />
    <ext value=".flac" />
    <ext value=".tta" />
    <ext value=".alac" />
    <ext value=".m4a" />
    <ext value=".aac" />
    <ext value=".wv" />
    <ext value=".wav" />
    <depend dll="bass.dll" />
    <depend dll="bass_aac.dll" />
    <depend dll="bass_alac.dll" />
    <depend dll="bass_ape.dll" />
    <depend dll="bass_flac.dll" />
    <depend dll="bass_mpc.dll" />
    <depend dll="bass_tta.dll" />
    <depend dll="bass_wv.dll" />
  </codecs>


  <codecs
    enable="0" priority="10"
    name="CDXA Reader"
    pathflag="file"
    path="cdxareader.dll"
    category="dsfilter"
    type="src" 
    clsid="{D367878E-F3B8-4235-A968-F378EF1B9A44}" >
    <protocol value="file" />
    <checkbyte value="0,4,,52494646,8,4,,43445841" />
    <ext value=".dat" />
  </codecs>

  <codecs
    enable="0" priority="10"
    name="CDDA Reader"
    pathflag="file"
    path="cddareader.dll"
    category="dsfilter"
    type="src"
    clsid="{54A35221-2C8D-4a31-A5DF-6D809847E393}" >
    <protocol value="file" />
    <checkbyte value="0,4,,52494646,8,4,,43444441" />
    <ext value=".cda" />
  </codecs>

  <codecs
    enable="0" priority="10"
    name="Pmp Source"
    pathflag="file"
    path="pmpsplt.ax"
    category="dsfilter"
    type="src"
    clsid="{E117D42B-839C-498A-95DA-647BC90E2B8F}" >
    <protocol value="file" />
    <checkbyte value="0,4,,706D706D" />
    <ext value=".pmp" />
  </codecs>

  <!------ Splitters ------>
  <codecs
    enable="1" priority="10"
    name="MP4 Splitter"
    pathflag="file"
    path="mp4splitter.ax"
    category="dsfilter"
    type="splt"
    clsid="{61F47056-E400-43D3-AF1E-AB7DFFD4C4AD}" >
    <mediatype major="MEDIATYPE_Stream" sub="MEDIASUBTYPE_MP4"/>
  </codecs>

  <codecs
    enable="1" priority="10"
    name="System AVI Splitter"
    pathflag="reg"
    category="dsfilter"
    type="splt"
    clsid="{1B544C20-FD0B-11CE-8C63-00AA0044B51E}" >
    <mediatype major="MEDIATYPE_Stream" sub="MEDIASUBTYPE_Avi" />
    <ext value=".avi" />
  </codecs>

  <codecs
    enable="1" priority="10"
    name="Matroska Splitter"
    pathflag="file"
    path="matroskasplitter.ax"
    category="dsfilter"
    type="splt"
    clsid="{149D2E01-C32E-4939-80F6-C07B81015A7A}" >
    <mediatype major="MEDIATYPE_Stream" sub="MEDIASUBTYPE_Matroska"/>
    <ext value=".mkv"/>
  </codecs>

  <codecs
    enable="1" priority="10"
    name="RealMedia Splitter"
    pathflag="file"
    path="realmediasplitter.ax"
    category="dsfilter"
    type="splt"
    clsid="{E21BE468-5C18-43EB-B0CC-DB93A847D769}" >
    <ext value=".ra"/>
    <ext value=".ram"/>
    <ext value=".rm"/>
    <ext value=".rmvb"/>
    <mediatype major="MEDIATYPE_Stream" sub="MEDIASUBTYPE_RealMedia"/>
    <depend dll="real\14_43260.dll"/>
    <depend dll="real\28_83260.dll"/>
    <depend dll="real\atrc.dll"/>
    <depend dll="real\cook.dll"/>
    <depend dll="real\dnet3260.dll"/>
    <depend dll="real\drv2.dll"/>
    <depend dll="real\drvc.dll"/>
    <depend dll="real\raac.dll"/>
    <depend dll="real\ralf.dll"/>
    <depend dll="real\sipr.dll"/>
    <depend dll="pncrt.dll"/>
  </codecs>

  <codecs
    enable="1" priority="10"
    name="MPC AVI Splitter"
    pathflag="file"
    path="avisplitter.ax"
    category="dsfilter"
    type="splt"
    clsid="{9736D831-9D6C-4E72-B6E7-560EF9181001}" >
    <mediatype major="MEDIATYPE_Stream" sub="MEDIASUBTYPE_Avi" />
    <ext value=".avi" />
  </codecs>

  <codecs
    enable="1" priority="10"
    name="Mpeg Splitter"
    pathflag="file"
    path="mpegsplitter.ax"
    category="dsfilter"
    type="splt"
    clsid="{DC257063-045F-4BE2-BD5B-E12279C464F0}" >
    <mediatype major="MEDIATYPE_Stream" sub="MEDIASUBTYPE_MPEG1System"/>
    <mediatype major="MEDIATYPE_Stream" sub="MEDIASUBTYPE_MPEG2_PROGRAM"/>
    <mediatype major="MEDIATYPE_Stream" sub="MEDIASUBTYPE_MPEG2_TRANSPORT"/>
    <mediatype major="MEDIATYPE_Stream" sub="MEDIASUBTYPE_MPEG2_PVA"/>
  </codecs>

  <codecs
    enable="1" priority="10"
    name="FLV Splitter"
    pathflag="file"
    path="flvsplitter.ax"
    category="dsfilter"
    type="splt"
    clsid="{47E792CF-0BBE-4F7A-859C-194B0768650A}" >
    <ext value=".flv"/>
    <mediatype major="MEDIATYPE_Stream" sub="MEDIASUBTYPE_FLV"/>
  </codecs>

  <codecs
    enable="1" priority="10"
    name="Mpa Splitter"
    pathflag="file"
    path="mpasplitter.ax"
    category="dsfilter"
    type="splt"
    clsid="{0E9D4BF7-CBCB-46C7-BD80-4EF223A3DC2B}" >
    <ext value=".mpg"/>
    <ext value=".mpeg"/>
    <ext value=".mp3"/>
    <mediatype major="MEDIATYPE_Stream" sub="MEDIASUBTYPE_MPEG1Audio"/>
    <!--mediatype major="MEDIATYPE_Stream" sub="{ABCDEF00-0000-0000-0000-000000000001}"/>
    <mediatype major="MEDIATYPE_Stream" sub="{ABCDEF00-0000-0000-0000-000000000003}"/>
    <mediatype major="MEDIATYPE_Stream" sub="{ABCDEF00-0000-0000-0000-000000000004}"/-->
  </codecs>

  <codecs
    enable="1" priority="10"
    name="Haali Media Splitter"
    pathflag="file"
    path="splitter.ax"
    category="dsfilter"
    type="splt"
    clsid="{564FD788-86C9-4444-971E-CC4A243DA150}" >
    <mediatype major="MEDIATYPE_Stream" sub="MEDIASUBTYPE_HaaliAVI"/>
    <mediatype major="MEDIATYPE_Stream" sub="MEDIASUBTYPE_MP4"/>
    <mediatype major="MEDIATYPE_Stream" sub="MEDIASUBTYPE_MPEG2_TRANSPORT"/>
    <depend dll="mkzlib.dll"/>
    <depend dll="mkunicode.dll"/>
  </codecs>

  <codecs
    enable="1" priority="10"
    name="Ogg Splitter"
    pathflag="file"
    path="oggsplitter.ax"
    category="dsfilter"
    type="splt"
    clsid="{9FF48807-E133-40AA-826F-9B2959E5232D}" >
    <mediatype major="MEDIATYPE_Stream" sub="MEDIASUBTYPE_Ogg" />
    <ext value=".ogg" />
  </codecs>

  <codecs
    enable="1" priority="10"
    name="Pmp Splitter"
    pathflag="file"
    path="pmpsplt.ax"
    category="dsfilter"
    type="splt"
    clsid="{412C98D0-B46E-4FFA-92E1-4016782EE0AB}" >
    <mediatype major="MEDIATYPE_Stream" sub="MEDIASUBTYPE_PMP" />
    <ext value=".pmp" />
  </codecs>

  <codecs
    enable="1" priority="10"
    name="Wav Splitter"
    pathflag="file"
    path="wavsplitter.dll"
    category="dsfilter"
    type="splt"
    clsid="{97ACFCC2-D036-660D-BC7D-16A003388BE5}" >
    <mediatype major="MEDIATYPE_Stream" sub="MEDIASUBTYPE_MPEG1Audio" />
    <mediatype major="MEDIATYPE_Stream" sub="MEDIASUBTYPE_WAVE" />
    <ext value=".wav" />
  </codecs>

  <codecs
    enable="1" priority="10"
    name="WebM Splitter Filter"
    pathflag="file"
    path="webmsplit.dll"
    category="dsfilter"
    type="splt"
    clsid="{ED3110F8-5211-11DF-94AF-0026B977EEAA}" >
    <mediatype major="MEDIATYPE_Stream" sub="MEDIASUBTYPE_Matroska" />
  </codecs>


  <!--codecs
    enable="0" priority="10"
    name="Player Windows Media Splitter"
    pathflag="file"
    path="wmsplitter.ax"
    category="dsfilter"
    type="splt"
    clsid="{97CAC3E3-DB62-4F72-926A-CACD734CB182}" >
    <mediatype major="MEDIATYPE_Stream" sub="{6B6D0801-9ADA-11D0-A520-00A0D10129C0}"/>
  </codecs-->


  <!------ Video/Audio Decoders ------>
  <codecs
    enable="1" priority="10"
    name="CoreAVC Video Decoder"
    pathflag="file"
    path="coreavc.ax"
    category="dsfilter"
    type="vdec"
    clsid="{09571A4B-F1FE-4C60-9760-DE6D310C7C31}" >
    <mediatype major="MEDIATYPE_Video" sub="MEDIASUBTYPE_avc1"/>
    <mediatype major="MEDIATYPE_Video" sub="MEDIASUBTYPE_AVC1"/>
    <mediatype major="MEDIATYPE_Video" sub="MEDIASUBTYPE_h264"/>
    <mediatype major="MEDIATYPE_Video" sub="MEDIASUBTYPE_H264"/>
    <mediatype major="MEDIATYPE_Video" sub="MEDIASUBTYPE_x264"/>
    <mediatype major="MEDIATYPE_Video" sub="MEDIASUBTYPE_X264"/>
    <mediatype major="MEDIATYPE_Video" sub="MEDIASUBTYPE_VSSH"/>
    <mediatype major="MEDIATYPE_Video" sub="MEDIASUBTYPE_H264_bis"/>
    <mediatype major="MEDIATYPE_Video" sub="MEDIASUBTYPE_ArcsoftH264"/>
  </codecs>

  <codecs
    enable="1" priority="10"
    name="CoreAAC Audio Decoder"
    pathflag="file"
    path="coreaac.ax"
    category="dsfilter"
    type="adec"
    clsid="{6AC7C19E-8CA0-4E3D-9A9F-2881DE29E0AC}" >
    <mediatype major="MEDIATYPE_Audio" sub="MEDIASUBTYPE_AAC"/>
    <mediatype major="MEDIATYPE_Audio" sub="MEDIASUBTYPE_MP4A"/>
  </codecs>

  <codecs
    enable="1" priority="10"
    name="CyberLink H.264/AVC Decoder (PDVD8)"
    pathflag="file"
    path="cl264dec.ax"
    category="dsfilter"
    type="vdec"
    clsid="{C16541FF-49ED-4DEA-9126-862F57722E31}" >
    <mediatype major="{A6F869FD-E176-4228-A9CD-11B0041FC391}" sub="MEDIASUBTYPE_H264_bis"/>
    <mediatype major="{A6F869FD-E176-4228-A9CD-11B0041FC392}" sub="MEDIASUBTYPE_H264_bis"/>
    <mediatype major="{0F24EDB7-5D9E-49AC-B8EF-374A5D450BF6}" sub="MEDIASUBTYPE_H264_bis"/>
    <mediatype major="{0F24EDB7-5D9E-49AC-B8EF-374A5D450BF7}" sub="MEDIASUBTYPE_H264_bis"/>
    <mediatype major="{43DC7A79-60B4-40B5-A3E7-963F9B35DC11}" sub="MEDIASUBTYPE_H264_bis"/>
    <mediatype major="{43DC7A79-60B4-40B5-A3E7-963F9B35DC12}" sub="MEDIASUBTYPE_H264_bis"/>
    <mediatype major="{E2522457-EB83-45B1-B45E-B298786D0E70}" sub="MEDIASUBTYPE_H264_bis"/>
    <mediatype major="MEDIATYPE_Video" sub="MEDIASUBTYPE_H264_bis"/>
    <mediatype major="MEDIATYPE_Video" sub="MEDIASUBTYPE_DAVC"/>
    <mediatype major="MEDIATYPE_Video" sub="MEDIASUBTYPE_AVC1"/>
    <mediatype major="MEDIATYPE_Video" sub="MEDIASUBTYPE_VSSH"/>
    <mediatype major="MEDIATYPE_Video" sub="MEDIASUBTYPE_H264"/>
    <mediatype major="MEDIATYPE_Video" sub="MEDIASUBTYPE_x264"/>
  </codecs>

  <codecs
    enable="1" priority="10"
    name="RealAudio Decoder"
    pathflag="file"
    path="realmediasplitter.ax"
    category="dsfilter"
    type="adec"
    clsid="{941A4793-A705-4312-8DFC-C11CA05F397E}" >
    <ext value=".ra"/>
    <ext value=".ram"/>
    <ext value=".rm"/>
    <ext value=".rmvb"/>
    <preload dll="pncrt.dll"/>
    <mediatype major="MEDIATYPE_Audio" sub="MEDIASUBTYPE_14_4"/>
    <mediatype major="MEDIATYPE_Audio" sub="MEDIASUBTYPE_28_8"/>
    <mediatype major="MEDIATYPE_Audio" sub="MEDIASUBTYPE_ATRC"/>
    <mediatype major="MEDIATYPE_Audio" sub="MEDIASUBTYPE_COOK"/>
    <mediatype major="MEDIATYPE_Audio" sub="MEDIASUBTYPE_DNET"/>
    <mediatype major="MEDIATYPE_Audio" sub="MEDIASUBTYPE_SIPR"/>
    <mediatype major="MEDIATYPE_Audio" sub="MEDIASUBTYPE_AAC"/>
    <mediatype major="MEDIATYPE_Audio" sub="MEDIASUBTYPE_RAAC"/>
    <mediatype major="MEDIATYPE_Audio" sub="MEDIASUBTYPE_RACP"/>
  </codecs>

  <codecs
    enable="1" priority="10"
    name="RealVideo Decoder"
    pathflag="file"
    path="realmediasplitter.ax"
    category="dsfilter"
    type="vdec"
    clsid="{238D0F23-5DC9-45A6-9BE2-666160C324DD}" >
    <ext value=".ra"/>
    <ext value=".ram"/>
    <ext value=".rm"/>
    <ext value=".rmvb"/>
    <preload dll="pncrt.dll"/>
    <mediatype major="MEDIATYPE_Video" sub="MEDIASUBTYPE_RV20"/>
    <mediatype major="MEDIATYPE_Video" sub="MEDIASUBTYPE_RV30"/>
    <mediatype major="MEDIATYPE_Video" sub="MEDIASUBTYPE_RV40"/>
    <mediatype major="MEDIATYPE_Video" sub="MEDIASUBTYPE_RV41"/>
  </codecs>

  <codecs
    enable="1" priority="10"
    name="CyberLink Video/SP Decoder(PDVD8)"
    pathflag="file"
    path="clvsd.ax"
    category="dsfilter"
    type="vdec"
    clsid="{37991D68-42A3-40E3-8C05-037170E1A42A}" >
    <mediatype major="MEDIATYPE_Video" sub="MEDIASUBTYPE_MPEG1Packet"/>
    <mediatype major="MEDIATYPE_Video" sub="MEDIASUBTYPE_MPEG1Payload"/>
    <mediatype major="MEDIATYPE_Video" sub="MEDIASUBTYPE_MPEG2_VIDEO"/>
    <mediatype major="MEDIATYPE_MPEG2_PES" sub="MEDIASUBTYPE_MPEG2_VIDEO"/>
    <mediatype major="MEDIATYPE_DVD_ENCRYPTED_PACK" sub="MEDIASUBTYPE_MPEG2_VIDEO"/>
    <mediatype major="{a6f869fd-e176-4228-a9cd-11b0041fc391}" sub="MEDIASUBTYPE_MPEG2_VIDEO"/>
    <mediatype major="{a6f869fd-e176-4228-a9cd-11b0041fc392}" sub="MEDIASUBTYPE_MPEG2_VIDEO"/>
    <mediatype major="{dddd8260-5fcb-4ef2-b88a-2330b73a46c0}" sub="MEDIASUBTYPE_MPEG2_VIDEO"/>
    <mediatype major="{43dc7a79-60b4-40b5-a3e7-963f9b35dc11}" sub="MEDIASUBTYPE_MPEG2_VIDEO"/>
    <mediatype major="{43dc7a79-60b4-40b5-a3e7-963f9b35dc12}" sub="MEDIASUBTYPE_MPEG2_VIDEO"/>
    <mediatype major="{e2522457-eb83-45b1-b45e-b298786d0e70}" sub="MEDIASUBTYPE_MPEG2_VIDEO"/>
    <ext value=".mpg"/>
    <ext value=".mpeg"/>
    <ext value=".vob"/>
  </codecs>

  <codecs
    enable="1" priority="10"
    name="MPEG2 Decoder Filter"
    pathflag="file"
    path="mpeg2decfilter.ax"
    category="dsfilter"
    type="vdec"
    clsid="{39F498AF-1A09-4275-B193-673B0BA3D478}" >
    <mediatype major="MEDIATYPE_DVD_ENCRYPTED_PACK" sub="MEDIASUBTYPE_MPEG2_VIDEO"/>
    <mediatype major="MEDIATYPE_MPEG2_PACK" sub="MEDIASUBTYPE_MPEG2_VIDEO"/>
    <mediatype major="MEDIATYPE_MPEG2_PES" sub="MEDIASUBTYPE_MPEG2_VIDEO"/>
    <mediatype major="MEDIATYPE_Video" sub="MEDIASUBTYPE_MPEG2_VIDEO"/>
    <mediatype major="MEDIATYPE_Video" sub="MEDIASUBTYPE_MPEG1Packet"/>
    <mediatype major="MEDIATYPE_Video" sub="MEDIASUBTYPE_MPEG1Payload"/>
    <ext value=".mpg" />
    <ext value=".mpeg" />
  </codecs>


  <codecs
    enable="1" priority="10"
    name="WMAudio Decoder DMO"
    pathflag="reg"
    type="adec"
    category="dmo"
    catedata="{57F2DB8B-E6BB-4513-9D43-DCD2A6593125},{2EEB4ADF-4578-4D10-BCA7-BB955F56320A}"
    clsid="{94297043-BD82-4DFD-B0DE-8177739C6D20}" >
    <mediatype major="MEDIATYPE_Audio" sub="MEDIASUBTYPE_WMA9_00" />
    <mediatype major="MEDIATYPE_Audio" sub="MEDIASUBTYPE_WMA9_01" />
    <mediatype major="MEDIATYPE_Audio" sub="MEDIASUBTYPE_WMA9_02" />
    <mediatype major="MEDIATYPE_Audio" sub="MEDIASUBTYPE_WMA9_03" />
    <ext value=".wmv"/>
    <ext value=".wma"/>
    <ext value=".asf"/>
  </codecs>

  <codecs
    enable="1" priority="10"
  name="WMVideo Decoder DMO"
  pathflag="reg"
  type="vdec"
  category="dmo"
  catedata="{4A69B442-28BE-4991-969C-B500ADF5D8A8},{82D353DF-90BD-4382-8BC2-3F6192B76E34}"
  clsid="{94297043-BD82-4DFD-B0DE-8177739C6D20}" >
    <mediatype major="MEDIATYPE_Video" sub="MEDIASUBTYPE_WMV1" />
    <mediatype major="MEDIATYPE_Video" sub="MEDIASUBTYPE_WMV2" />
    <mediatype major="MEDIATYPE_Video" sub="MEDIASUBTYPE_WMV3" />
    <mediatype major="MEDIATYPE_Video" sub="MEDIASUBTYPE_WMVA" />
    <mediatype major="MEDIATYPE_Video" sub="MEDIASUBTYPE_WMVR" />
    <mediatype major="MEDIATYPE_Video" sub="MEDIASUBTYPE_WMVP" />
    <mediatype major="MEDIATYPE_Video" sub="MEDIASUBTYPE_WVP2" />
    <ext value=".wmv"/>
    <ext value=".wma"/>
    <ext value=".asf"/>
  </codecs>

  <!--codecs
    name="Player WM Video Decoder DMO"
    pathflag="inner"
    clsid="{4E57DF44-F943-4919-BF59-9D3F464BD450}"
    category="dmo"
    catedata="{82D353DF-90BD-4382-8BC2-3F6192B76E34}"
    type="vdec"
    merit="0x00400000" >
    <mediatype major="MEDIATYPE_Video" sub="MEDIASUBTYPE_WMV1" />
    <mediatype major="MEDIATYPE_Video" sub="MEDIASUBTYPE_WMV2" />
    <mediatype major="MEDIATYPE_Video" sub="MEDIASUBTYPE_WMV3" />
    <mediatype major="MEDIATYPE_Video" sub="MEDIASUBTYPE_WMVA" />
    <mediatype major="MEDIATYPE_Video" sub="MEDIASUBTYPE_WMVR" />
    <mediatype major="MEDIATYPE_Video" sub="MEDIASUBTYPE_WMVP" />
    <mediatype major="MEDIATYPE_Video" sub="MEDIASUBTYPE_WVP2" />
    <ext value=".wmv" />
    <ext value=".wma" />
    <ext value=".asf" />
  </codecs>

  <codecs
  name="SYS WM Video Decoder DMO"
  pathflag="codecs"
  path="qasf.dll"
  clsid="{82D353DF-90BD-4382-8BC2-3F6192B76E34}"
  category="unknown" >
  </codecs>


  <codecs
    name="Player WM Audio Decoder DMO"
    pathflag="inner"
    clsid="{4E57DF44-F943-4919-BF59-9D3F464BD450}"
    category="dmo"
    catedata="{2EEB4ADF-4578-4D10-BCA7-BB955F56320A}"
    type="adec"
    merit="0x00400000" >
    <mediatype major="MEDIATYPE_Audio" sub="MEDIASUBTYPE_WMA9_00" />
    <mediatype major="MEDIATYPE_Audio" sub="MEDIASUBTYPE_WMA9_01" />
    <mediatype major="MEDIATYPE_Audio" sub="MEDIASUBTYPE_WMA9_02" />
    <mediatype major="MEDIATYPE_Audio" sub="MEDIASUBTYPE_WMA9_03" />
    <ext value=".wmv" />
    <ext value=".wma" />
    <ext value=".asf" />
  </codecs>

    <codecs
  name="SYS WM Video Decoder DMO"
  pathflag="file"
  path="qasf.dll"
  clsid="{2EEB4ADF-4578-4D10-BCA7-BB955F56320A}"
  category="unknown" >
  </codecs>

  <codecs
	name="Player WM Screen Decoder DMO"
	pathflag="inner"
	clsid="{4E57DF44-F943-4919-BF59-9D3F464BD450}"
	category="dmo"
	catedata="{7BAFB3B1-D8F4-4279-9253-27DA423108DE}"
	type="vdec"
	merit="0x00400000" >
    <mediatype major="MEDIATYPE_Video" sub="{3153534d-0000-0010-8000-00aa00389b71}" />
    <mediatype major="MEDIATYPE_Video" sub="{3253534d-0000-0010-8000-00aa00389b71}" />
  </codecs>

  <codecs
	name="Player WM Voice Decoder DMO"
	pathflag="inner"
	clsid="{4E57DF44-F943-4919-BF59-9D3F464BD450}"
	category="dmo"
	catedata="{874131CB-4ECC-443B-8948-746B89595D20}"
	type="adec"
	merit="0x00400000" >
    <mediatype major="MEDIATYPE_Audio" sub="{0000000a-0000-0010-8000-00aa00389b71}" />
    <mediatype major="MEDIATYPE_Audio" sub="{0000000b-0000-0010-8000-00aa00389b71}" />
    <ext value=".wmv" />
    <ext value=".wma" />
    <ext value=".asf" />
  </codecs-->

  <codecs
    enable="1" priority="10"
  name="VMware Movie Decoder"
  pathflag="file"
  path="vmnc.dll"
  category="vfw"
  catedata="vidc,vmnc"
  type="vdec"
  >
    <mediatype major="MEDIATYPE_Video" sub="MEDIASUBTYPE_VMnc" />
  </codecs>

  <codecs
    enable="1" priority="10"
	name="VP6 Decompressor"
	pathflag="file"
	path="vp6dec.ax"
	category="dsfilter"
	type="vdec"
	clsid="{01CFC007-C263-420A-80DC-2988DA4C6105}" >
    <mediatype major="MEDIATYPE_Video" sub="MEDIASUBTYPE_VP60" />
    <mediatype major="MEDIATYPE_Video" sub="MEDIASUBTYPE_VP61" />
    <mediatype major="MEDIATYPE_Video" sub="MEDIASUBTYPE_VP62" />
  </codecs>


  <codecs
    enable="1" priority="10"
	name="VP7 Decompressor"
	pathflag="file"
	path="vp7dec.ax"
	category="dsfilter"
	type="vdec"
	clsid="{C204438D-6E1A-4309-B09C-0C0F749863AF}" >
    <mediatype major="MEDIATYPE_Video" sub="MEDIASUBTYPE_VP70" />
    <mediatype major="MEDIATYPE_Video" sub="MEDIASUBTYPE_VP71" />
  </codecs>

  <codecs
    enable="1" priority="10"
    name="WebM VP8 Decoder Filter"
    pathflag="file"
    path="vp8decoder.dll"
    category="dsfilter"
    type="vdec"
    clsid="{ED3110F3-5211-11DF-94AF-0026B977EEAA}" >
    <mediatype major="MEDIATYPE_Video" sub="MEDIASUBTYPE_VP80" />
  </codecs>

  <!--AC3-->
  <codecs
    enable="1" priority="10"
    name="AC3Filter"
    pathflag="file"
    path="ac3filter.dll"
    category="dsfilter"
    type="adec"
    clsid="{A753A1EC-973E-4718-AF8E-A3F554D45C44}" >
    <mediatype major="MEDIATYPE_MPEG2_PES" sub="MEDIASUBTYPE_MPEG1AudioPayload" />
    <mediatype major="MEDIATYPE_DVD_ENCRYPTED_PACK" sub="MEDIASUBTYPE_MPEG1AudioPayload" />
    <mediatype major="MEDIATYPE_Audio" sub="MEDIASUBTYPE_WAVE_DOLBY_AC3" />
    <!--mediatype major="MEDIATYPE_Audio" sub="MEDIASUBTYPE_WAVE_DTS" /-->
    <!--mediatype major="MEDIATYPE_Audio" sub="MEDIASUBTYPE_DOLBY_AC3" /-->
    <ext value=".wav" />
    <ext value=".dts" />
  </codecs>

  <!--ACE-->
  <codecs
    enable="1" priority="10"
	name="ACELP.net Sipro Lab Audio Decoder"
	pathflag="file"
	path="acelpdec.ax"
	category="dsfilter"
	type="adec"
	clsid="{4009F700-AEBA-11D1-8344-00C04FB92EB7}" >
    <mediatype major="MEDIATYPE_Audio" sub="{00000130-0000-0010-8000-00aa00389b71}" />
    <ext value=".ace" />
  </codecs>

  <!--- FFDSHOW --->
  <codecs
    enable="1" priority="6"
    name="ffdshow DXVA Video Decoder"
    pathflag="file"
    path="ffdshow.ax"
    category="dsfilter"
    type="vdec"
    clsid="{0B0EFF97-C750-462C-9488-B10E7D87F1A6}" >
    <mediatype major="MEDIATYPE_DVD_ENCRYPTED_PACK" sub="MEDIASUBTYPE_AVC1"/>
    <mediatype major="MEDIATYPE_DVD_ENCRYPTED_PACK" sub="MEDIASUBTYPE_WVC1"/>
    <mediatype major="MEDIATYPE_Video" sub="MEDIASUBTYPE_H264"/>
    <mediatype major="MEDIATYPE_Video" sub="MEDIASUBTYPE_h264"/>
    <mediatype major="MEDIATYPE_Video" sub="MEDIASUBTYPE_AVC1"/>
    <mediatype major="MEDIATYPE_Video" sub="MEDIASUBTYPE_avc1"/>
    <mediatype major="MEDIATYPE_Video" sub="MEDIASUBTYPE_CCV1"/>
    <mediatype major="MEDIATYPE_Video" sub="MEDIASUBTYPE_WVC1"/>
    <mediatype major="MEDIATYPE_Video" sub="MEDIASUBTYPE_wvc1"/>
    <depend dll="ff_kernelDeint.dll"/>
    <depend dll="ff_liba52.dll"/>
    <depend dll="ff_libdts.dll"/>
    <depend dll="ff_libfaad2.dll"/>
    <depend dll="ff_libmad.dll"/>
    <depend dll="ff_samplerate.dll"/>
    <depend dll="ff_unrar.dll"/>
    <depend dll="ff_wmv9.dll"/>
    <depend dll="ffmpeg.dll"/>
    <!--depend dll="ffmpegmt.dll"/-->
    <depend dll="libmpeg2_ff.dll"/>
  </codecs>

  <codecs
    enable="1" priority="10"
    name="ffdshow raw video codecs"
    pathflag="file"
    path="ffdshow.ax"
    category="dsfilter"
    type="vdec"
    clsid="{0B390488-D80F-4A68-8408-48DC199F0E97}" >
    <mediatype major="MEDIATYPE_Video" sub="GUID_NULL" />
    <!--depend dll="ffdshow.ax.manifest"/-->
    <depend dll="ff_kernelDeint.dll"/>
    <depend dll="ff_liba52.dll"/>
    <depend dll="ff_libdts.dll"/>
    <depend dll="ff_libfaad2.dll"/>
    <depend dll="ff_libmad.dll"/>
    <depend dll="ff_samplerate.dll"/>
    <depend dll="ff_unrar.dll"/>
    <depend dll="ff_wmv9.dll"/>
    <depend dll="ffmpeg.dll"/>
    <!--depend dll="ffmpegmt.dll"/-->
    <depend dll="libmpeg2_ff.dll"/>
  </codecs>

  <codecs
    enable="1" priority="10"
    name="ffdshow Video Decoder"
    pathflag="file"
    path="ffdshow.ax"
    category="dsfilter"
    type="vdec"
    clsid="{04FE9017-F873-410E-871E-AB91661A4EF7}" >
    <mediatype major="MEDIATYPE_Video" sub="GUID_NULL" />
    <mediatype major="MEDIATYPE_DVD_ENCRYPTED_PACK" sub="GUID_NULL" />
    <mediatype major="MEDIATYPE_DVD_ENCRYPTED_PACK" sub="MEDIASUBTYPE_MPEG2_VIDEO" />
    <mediatype major="MEDIATYPE_DVD_ENCRYPTED_PACK" sub="MEDIASUBTYPE_AVC1" />
    <mediatype major="MEDIATYPE_DVD_ENCRYPTED_PACK" sub="MEDIASUBTYPE_WVC1" />
    <mediatype major="MEDIATYPE_Video" sub="MEDIASUBTYPE_XVID" />
    <mediatype major="MEDIATYPE_Video" sub="MEDIASUBTYPE_xvid" />
    <mediatype major="MEDIATYPE_Video" sub="MEDIASUBTYPE_DIVX" />
    <mediatype major="MEDIATYPE_Video" sub="MEDIASUBTYPE_divx" />
    <mediatype major="MEDIATYPE_Video" sub="MEDIASUBTYPE_DX50" />
    <mediatype major="MEDIATYPE_Video" sub="MEDIASUBTYPE_dx50" />
    <mediatype major="MEDIATYPE_Video" sub="MEDIASUBTYPE_H264" />
    <mediatype major="MEDIATYPE_Video" sub="MEDIASUBTYPE_h264" />
    <mediatype major="MEDIATYPE_Video" sub="MEDIASUBTYPE_AVC1" />
    <mediatype major="MEDIATYPE_Video" sub="MEDIASUBTYPE_avc1" />
    <mediatype major="MEDIATYPE_Video" sub="MEDIASUBTYPE_H263" />
    <mediatype major="MEDIATYPE_Video" sub="MEDIASUBTYPE_h263" />
    <mediatype major="MEDIATYPE_Video" sub="MEDIASUBTYPE_DIV3" />
    <mediatype major="MEDIATYPE_Video" sub="MEDIASUBTYPE_div3" />
    <mediatype major="MEDIATYPE_Video" sub="MEDIASUBTYPE_MP43" />
    <mediatype major="MEDIATYPE_Video" sub="MEDIASUBTYPE_mp43" />
    <mediatype major="MEDIATYPE_Video" sub="MEDIASUBTYPE_MP42" />
    <mediatype major="MEDIATYPE_Video" sub="MEDIASUBTYPE_mp42" />
    <mediatype major="MEDIATYPE_Video" sub="MEDIASUBTYPE_MP41" />
    <mediatype major="MEDIATYPE_Video" sub="MEDIASUBTYPE_mp41" />
    <mediatype major="MEDIATYPE_Video" sub="MEDIASUBTYPE_MP4V" />
    <mediatype major="MEDIATYPE_Video" sub="MEDIASUBTYPE_mp4v" />
    <mediatype major="MEDIATYPE_Video" sub="MEDIASUBTYPE_MP4S" />
    <mediatype major="MEDIATYPE_Video" sub="MEDIASUBTYPE_mp4s" />
    <mediatype major="MEDIATYPE_Video" sub="MEDIASUBTYPE_SEDG" />
    <mediatype major="MEDIATYPE_Video" sub="MEDIASUBTYPE_sedg" />
    <mediatype major="MEDIATYPE_Video" sub="MEDIASUBTYPE_WMV1" />
    <mediatype major="MEDIATYPE_Video" sub="MEDIASUBTYPE_wmv1" />
    <mediatype major="MEDIATYPE_Video" sub="MEDIASUBTYPE_WMV2" />
    <mediatype major="MEDIATYPE_Video" sub="MEDIASUBTYPE_wmv2" />
    <mediatype major="MEDIATYPE_Video" sub="MEDIASUBTYPE_WMV3" />
    <mediatype major="MEDIATYPE_Video" sub="MEDIASUBTYPE_wmv3" />
    <mediatype major="MEDIATYPE_Video" sub="MEDIASUBTYPE_WVC1" />
    <mediatype major="MEDIATYPE_Video" sub="MEDIASUBTYPE_wvc1" />
    <mediatype major="MEDIATYPE_Video" sub="MEDIASUBTYPE_VP50" />
    <mediatype major="MEDIATYPE_Video" sub="MEDIASUBTYPE_vp50" />
    <mediatype major="MEDIATYPE_Video" sub="MEDIASUBTYPE_VP60" />
    <mediatype major="MEDIATYPE_Video" sub="MEDIASUBTYPE_vp60" />
    <mediatype major="MEDIATYPE_Video" sub="MEDIASUBTYPE_VP61" />
    <mediatype major="MEDIATYPE_Video" sub="MEDIASUBTYPE_vp61" />
    <mediatype major="MEDIATYPE_Video" sub="MEDIASUBTYPE_VP62" />
    <mediatype major="MEDIATYPE_Video" sub="MEDIASUBTYPE_vp62" />
    <mediatype major="MEDIATYPE_Video" sub="MEDIASUBTYPE_VP6F" />
    <mediatype major="MEDIATYPE_Video" sub="MEDIASUBTYPE_vp6f" />
    <mediatype major="MEDIATYPE_Video" sub="MEDIASUBTYPE_FLV4" />
    <mediatype major="MEDIATYPE_Video" sub="MEDIASUBTYPE_flv4" />
    <mediatype major="MEDIATYPE_Video" sub="MEDIASUBTYPE_HFYU" />
    <mediatype major="MEDIATYPE_Video" sub="MEDIASUBTYPE_hfyu" />
    <mediatype major="MEDIATYPE_Video" sub="MEDIASUBTYPE_3IV2" />
    <mediatype major="MEDIATYPE_Video" sub="MEDIASUBTYPE_3iv2" />
    <mediatype major="MEDIATYPE_Video" sub="MEDIASUBTYPE_3IVX" />
    <mediatype major="MEDIATYPE_Video" sub="MEDIASUBTYPE_3ivx" />
    <mediatype major="MEDIATYPE_Video" sub="MEDIASUBTYPE_MPEG1Packet" />
    <mediatype major="MEDIATYPE_Video" sub="MEDIASUBTYPE_MPEG1Payload" />
    <mediatype major="MEDIATYPE_Video" sub="MEDIASUBTYPE_MPEG2_VIDEO" />
    <mediatype major="MEDIATYPE_Video" sub="MEDIASUBTYPE_MPG2" />
    <mediatype major="MEDIATYPE_Video" sub="MEDIASUBTYPE_mpg2" />
    <mediatype major="MEDIATYPE_Video" sub="MEDIASUBTYPE_EM2V" />
    <mediatype major="MEDIATYPE_Video" sub="MEDIASUBTYPE_em2v" />
    <mediatype major="MEDIATYPE_Video" sub="MEDIASUBTYPE_MMES" />
    <mediatype major="MEDIATYPE_Video" sub="MEDIASUBTYPE_mmes" />
    <mediatype major="MEDIATYPE_Video" sub="MEDIASUBTYPE_VP31" />
    <mediatype major="MEDIATYPE_Video" sub="MEDIASUBTYPE_vp31" />
    <mediatype major="MEDIATYPE_Video" sub="MEDIASUBTYPE_TSCC" />
    <mediatype major="MEDIATYPE_Video" sub="MEDIASUBTYPE_tscc" />
    <mediatype major="MEDIATYPE_Video" sub="MEDIASUBTYPE_CRAM" />
    <mediatype major="MEDIATYPE_Video" sub="MEDIASUBTYPE_cram" />
    <mediatype major="MEDIATYPE_Video" sub="MEDIASUBTYPE_AVRN" />
    <mediatype major="MEDIATYPE_Video" sub="MEDIASUBTYPE_avrn" />
    <mediatype major="MEDIATYPE_Video" sub="MEDIASUBTYPE_FPS1" />
    <mediatype major="MEDIATYPE_Video" sub="MEDIASUBTYPE_fps1" />
    <mediatype major="MEDIATYPE_Video" sub="MEDIASUBTYPE_WMVP" />
    <mediatype major="MEDIATYPE_Video" sub="MEDIASUBTYPE_wmvp" />
    <mediatype major="MEDIATYPE_Video" sub="MEDIASUBTYPE_WVP2" />
    <mediatype major="MEDIATYPE_Video" sub="MEDIASUBTYPE_wvp2" />
    <mediatype major="MEDIATYPE_Video" sub="MEDIASUBTYPE_MJPG" />
    <mediatype major="MEDIATYPE_Video" sub="MEDIASUBTYPE_mjpg" />
    <mediatype major="MEDIATYPE_Video" sub="MEDIASUBTYPE_MJPA" />
    <mediatype major="MEDIATYPE_Video" sub="MEDIASUBTYPE_mjpa" />
    <mediatype major="MEDIATYPE_Video" sub="MEDIASUBTYPE_AMVV" />
    <mediatype major="MEDIATYPE_Video" sub="MEDIASUBTYPE_SP5X" />
    <mediatype major="MEDIATYPE_Video" sub="MEDIASUBTYPE_DVSD" />
    <mediatype major="MEDIATYPE_Video" sub="MEDIASUBTYPE_dvsd" />
    <mediatype major="MEDIATYPE_Video" sub="MEDIASUBTYPE_DV25" />
    <mediatype major="MEDIATYPE_Video" sub="MEDIASUBTYPE_dv25" />
    <mediatype major="MEDIATYPE_Video" sub="MEDIASUBTYPE_DV50" />
    <mediatype major="MEDIATYPE_Video" sub="MEDIASUBTYPE_dv50" />
    <mediatype major="MEDIATYPE_Video" sub="MEDIASUBTYPE_CDVC" />
    <mediatype major="MEDIATYPE_Video" sub="MEDIASUBTYPE_cdvc" />
    <mediatype major="MEDIATYPE_Video" sub="MEDIASUBTYPE_CDV5" />
    <mediatype major="MEDIATYPE_Video" sub="MEDIASUBTYPE_cdv5" />
    <mediatype major="MEDIATYPE_Video" sub="MEDIASUBTYPE_DVIS" />
    <mediatype major="MEDIATYPE_Video" sub="MEDIASUBTYPE_dvis" />
    <mediatype major="MEDIATYPE_Video" sub="MEDIASUBTYPE_PDVC" />
    <mediatype major="MEDIATYPE_Video" sub="MEDIASUBTYPE_pdvc" />
    <mediatype major="MEDIATYPE_Video" sub="MEDIASUBTYPE_YV12" />
    <mediatype major="MEDIATYPE_Video" sub="MEDIASUBTYPE_IYUV" />
    <mediatype major="MEDIATYPE_Video" sub="MEDIASUBTYPE_YUY2" />
    <mediatype major="MEDIATYPE_Video" sub="MEDIASUBTYPE_YUYV" />
    <!--mediatype major="MEDIATYPE_Video" sub="{56565955-0000-0010-8000-00aa00389b71}" / UYVV-->
    <mediatype major="MEDIATYPE_Video" sub="MEDIASUBTYPE_VYUY" />
    <mediatype major="MEDIATYPE_Video" sub="MEDIASUBTYPE_RGB32" />
    <mediatype major="MEDIATYPE_Video" sub="MEDIASUBTYPE_RGB24" />
    <mediatype major="MEDIATYPE_Video" sub="MEDIASUBTYPE_RGB555" />
    <mediatype major="MEDIATYPE_Video" sub="MEDIASUBTYPE_RGB565" />
    <depend dll="ff_kernelDeint.dll"/>
    <depend dll="ff_liba52.dll"/>
    <depend dll="ff_libdts.dll"/>
    <depend dll="ff_libfaad2.dll"/>
    <depend dll="ff_libmad.dll"/>
    <depend dll="ff_samplerate.dll"/>
    <depend dll="ff_unrar.dll"/>
    <depend dll="ff_wmv9.dll"/>
    <depend dll="ffmpeg.dll"/>
    <!--depend dll="ffmpegmt.dll"/-->
    <depend dll="libmpeg2_ff.dll"/>
  </codecs>

  <codecs
    enable="1" priority="10"
    name="ffdshow Audio Decoder"
    pathflag="file"
    path="ffdshow.ax"
    category="dsfilter"
    type="adec"
    clsid="{0F40E1E5-4F79-4988-B1A9-CC98794E6B55}" >
    <mediatype major="MEDIATYPE_Audio" sub="MEDIASUBTYPE_MP3" />
    <mediatype major="MEDIATYPE_Audio" sub="MEDIASUBTYPE_MPEG1AudioPayload" />
    <mediatype major="MEDIATYPE_Audio" sub="MEDIASUBTYPE_MPEG1Payload" />
    <mediatype major="MEDIATYPE_Audio" sub="MEDIASUBTYPE_MPEG1Packet" />
    <mediatype major="MEDIATYPE_Audio" sub="MEDIASUBTYPE_MPEG2_AUDIO" />
    <mediatype major="MEDIATYPE_MPEG2_PACK" sub="MEDIASUBTYPE_MPEG2_AUDIO" />
    <mediatype major="MEDIATYPE_MPEG2_PES" sub="MEDIASUBTYPE_MPEG2_AUDIO" />
    <mediatype major="MEDIATYPE_DVD_ENCRYPTED_PACK" sub="MEDIASUBTYPE_MPEG2_AUDIO" />
    <mediatype major="MEDIATYPE_Audio" sub="MEDIASUBTYPE_WAVE_DOLBY_AC3" />
    <mediatype major="MEDIATYPE_MPEG2_PES" sub="MEDIASUBTYPE_DOLBY_AC3" />
    <mediatype major="MEDIATYPE_MPEG2_PACK" sub="MEDIASUBTYPE_DOLBY_AC3" />
    <mediatype major="MEDIATYPE_Audio" sub="MEDIASUBTYPE_DOLBY_AC3" />
    <mediatype major="MEDIATYPE_DVD_ENCRYPTED_PACK" sub="MEDIASUBTYPE_DOLBY_AC3" />
    <mediatype major="MEDIATYPE_Audio" sub="MEDIASUBTYPE_WAVE_DTS" />
    <mediatype major="MEDIATYPE_MPEG2_PES" sub="MEDIASUBTYPE_DTS" />
    <mediatype major="MEDIATYPE_MPEG2_PACK" sub="MEDIASUBTYPE_DTS" />
    <mediatype major="MEDIATYPE_Audio" sub="MEDIASUBTYPE_DTS" />
    <mediatype major="MEDIATYPE_DVD_ENCRYPTED_PACK" sub="MEDIASUBTYPE_DTS" />
    <mediatype major="MEDIATYPE_MPEG2_PACK" sub="MEDIASUBTYPE_DVD_LPCM_AUDIO" />
    <mediatype major="MEDIATYPE_MPEG2_PES" sub="MEDIASUBTYPE_DVD_LPCM_AUDIO" />
    <mediatype major="MEDIATYPE_Audio" sub="MEDIASUBTYPE_DVD_LPCM_AUDIO" />
    <mediatype major="MEDIATYPE_DVD_ENCRYPTED_PACK" sub="MEDIASUBTYPE_DVD_LPCM_AUDIO" />
    <mediatype major="MEDIATYPE_Audio" sub="{0000aac0-0000-0010-8000-00aa00389b71}" />
    <mediatype major="MEDIATYPE_Audio" sub="MEDIASUBTYPE_AAC" />
    <mediatype major="MEDIATYPE_Audio" sub="MEDIASUBTYPE_MP4A" />
    <mediatype major="MEDIATYPE_Audio" sub="{0000706d-0000-0010-8000-00aa00389b71}" />
    <mediatype major="MEDIATYPE_Audio" sub="MEDIASUBTYPE_mp4a" />
    <mediatype major="MEDIATYPE_Audio" sub="MEDIASUBTYPE_WMA9_00" />
    <mediatype major="MEDIATYPE_Audio" sub="MEDIASUBTYPE_WMA9_01" />
    <mediatype major="MEDIATYPE_Audio" sub="MEDIASUBTYPE_AMR" />
    <mediatype major="MEDIATYPE_Audio" sub="MEDIASUBTYPE_SAMR" />
    <mediatype major="MEDIATYPE_Audio" sub="{00000062-0000-0010-8000-00aa00389b71}" />
    <mediatype major="MEDIATYPE_Audio" sub="{00000011-0000-0010-8000-00aa00389b71}" />
    <mediatype major="MEDIATYPE_Audio" sub="{00000061-0000-0010-8000-00aa00389b71}" />
    <mediatype major="MEDIATYPE_Audio" sub="MEDIASUBTYPE_IMA4" />
    <mediatype major="MEDIATYPE_Audio" sub="MEDIASUBTYPE_IMA_AMV" />
    <mediatype major="MEDIATYPE_Audio" sub="{46575341-0000-0010-8000-00aa00389b71}" />
    <mediatype major="MEDIATYPE_Audio" sub="KSDATAFORMAT_SUBTYPE_ADPCM" />
    <mediatype major="MEDIATYPE_Audio" sub="{00000200-0000-0010-8000-00aa00389b71}" />
    <mediatype major="MEDIATYPE_Audio" sub="{00000020-0000-0010-8000-00aa00389b71}" />
    <mediatype major="MEDIATYPE_Audio" sub="{00000045-0000-0010-8000-00aa00389b71}" />
    <mediatype major="MEDIATYPE_Audio" sub="MEDIASUBTYPE_FLAC" />
    <mediatype major="MEDIATYPE_Audio" sub="MEDIASUBTYPE_FLAC_FRAMED" />
    <mediatype major="MEDIATYPE_Audio" sub="MEDIASUBTYPE_TTA1" />
    <mediatype major="MEDIATYPE_Audio" sub="{0000566f-0000-0010-8000-00aa00389b71}" />
    <mediatype major="MEDIATYPE_Audio" sub="{00003313-0000-0010-8000-00aa00389b71}" />
    <mediatype major="MEDIATYPE_Audio" sub="{77616c61-0000-0010-8000-00aa00389b71}" />
    <mediatype major="MEDIATYPE_Audio" sub="KSDATAFORMAT_SUBTYPE_ALAW" />
    <mediatype major="MEDIATYPE_Audio" sub="KSDATAFORMAT_SUBTYPE_MULAW" />
    <mediatype major="MEDIATYPE_Audio" sub="MEDIASUBTYPE_ulaw" />
    <mediatype major="MEDIATYPE_Audio" sub="MEDIASUBTYPE_ULAW" />
    <mediatype major="MEDIATYPE_Audio" sub="{00000031-0000-0010-8000-00aa00389b71}" />
    <mediatype major="MEDIATYPE_Audio" sub="MEDIASUBTYPE_MAC3" />
    <mediatype major="MEDIATYPE_Audio" sub="MEDIASUBTYPE_MAC6" />
    <mediatype major="MEDIATYPE_Audio" sub="MEDIASUBTYPE_qdm2" />
    <mediatype major="MEDIATYPE_Audio" sub="MEDIASUBTYPE_QDM2" />
    <mediatype major="MEDIATYPE_Audio" sub="MEDIASUBTYPE_PCM_SOWT" />
    <mediatype major="MEDIATYPE_Audio" sub="MEDIASUBTYPE_PCM_sowt" />
    <mediatype major="MEDIATYPE_Audio" sub="MEDIASUBTYPE_PCM_TWOS" />
    <mediatype major="MEDIATYPE_Audio" sub="MEDIASUBTYPE_PCM_twos" />
    <mediatype major="MEDIATYPE_Audio" sub="MEDIASUBTYPE_PCM_IN32" />
    <mediatype major="MEDIATYPE_Audio" sub="MEDIASUBTYPE_PCM_in32" />
    <mediatype major="MEDIATYPE_Audio" sub="MEDIASUBTYPE_PCM_IN24" />
    <mediatype major="MEDIATYPE_Audio" sub="MEDIASUBTYPE_PCM_in24" />
    <mediatype major="MEDIATYPE_Audio" sub="MEDIASUBTYPE_PCM_fl32" />
    <mediatype major="MEDIATYPE_Audio" sub="MEDIASUBTYPE_PCM_FL32" />
    <mediatype major="MEDIATYPE_Audio" sub="MEDIASUBTYPE_PCM_fl64" />
    <mediatype major="MEDIATYPE_Audio" sub="MEDIASUBTYPE_PCM_FL64" />
    <mediatype major="MEDIATYPE_Audio" sub="{00000022-0000-0010-8000-00aa00389b71}" />
    <mediatype major="MEDIATYPE_Audio" sub="MEDIASUBTYPE_14_4" />
    <mediatype major="MEDIATYPE_Audio" sub="MEDIASUBTYPE_28_8" />
    <mediatype major="MEDIATYPE_Audio" sub="{00000401-0000-0010-8000-00aa00389b71}" />
    <mediatype major="MEDIATYPE_Audio" sub="{00000270-0000-0010-8000-00aa00389b71}" />
    <mediatype major="MEDIATYPE_Audio" sub="MEDIASUBTYPE_NELLYMOSER" />
    <mediatype major="MEDIATYPE_Audio" sub="MEDIASUBTYPE_Vorbis" />
    <mediatype major="MEDIATYPE_Audio" sub="MEDIASUBTYPE_Vorbis2" />
    <mediatype major="MEDIATYPE_Audio" sub="MEDIASUBTYPE_X_Vorbis" />
    <mediatype major="MEDIATYPE_Audio" sub="MEDIASUBTYPE_PCM" />
    <mediatype major="MEDIATYPE_Audio" sub="MEDIASUBTYPE_PCM_RAW" />
    <mediatype major="MEDIATYPE_Audio" sub="MEDIASUBTYPE_IEEE_FLOAT" />
    <mediatype major="MEDIATYPE_Audio" sub="KSDATAFORMAT_SUBTYPE_IEC61937_DOLBY_DIGITAL_PLUS" />
    <depend dll="ff_kernelDeint.dll"/>
    <depend dll="ff_liba52.dll"/>
    <depend dll="ff_libdts.dll"/>
    <depend dll="ff_libfaad2.dll"/>
    <depend dll="ff_libmad.dll"/>
    <depend dll="ff_samplerate.dll"/>
    <depend dll="ff_unrar.dll"/>
    <depend dll="ff_wmv9.dll"/>
    <depend dll="ffmpeg.dll"/>
    <!--depend dll="ffmpegmt.dll"/-->
    <depend dll="libmpeg2_ff.dll"/>
  </codecs>

  <!--codecs
    enable="1" priority="10"
  name="Haali Disk File Reader"
  pathflag="file"
  path="mkx.dll"
  category="dsfilter"
  clsid="{53D9DE0B-FC61-4650-9773-74D13CC7E582}" >
  </codecs-->

  <!--codecs
  name="Haali Disk File Reader"
  pathflag="file"
  path="mp4.dll"
  category="dsfilter"
  clsid="{B3DE7EDC-0CD4-4D07-B1C5-92219CD475CC}" >
  </codecs-->

  <!--codecs
  name="Haali Disk TS Parser"
  pathflag="file"
  path="ts.dll"
  category="dsfilter"
  clsid="{B841F346-4835-4DE8-AA5E-2E7CD2D4C435}" >
    <depend dll="mkunicode.dll" />
  </codecs-->

  <codecs
    enable="1" priority="10"
    name="MPC - MPA Decoder Filter"
    pathflag="file"
    path="mpadecfilter.ax"
    category="dsfilter"
    type="adec"
    clsid="{3D446B6F-71DE-4437-BE15-8CE47174340F}" >
    <mediatype major="MEDIATYPE_Audio" sub="MEDIASUBTYPE_MP3"/>
    <!--//  <mediatype major="MEDIATYPE_Audio,MEDIASUBTYPE_MPEG1AudioPayload
    //  <mediatype major="MEDIATYPE_Audio,MEDIASUBTYPE_MPEG1Payload
    //  <mediatype major="MEDIATYPE_Audio,MEDIASUBTYPE_MPEG1Packet-->
    <mediatype major="MEDIATYPE_DVD_ENCRYPTED_PACK" sub="MEDIASUBTYPE_MPEG2_AUDIO"/>
    <mediatype major="MEDIATYPE_MPEG2_PACK" sub="MEDIASUBTYPE_MPEG2_AUDIO"/>
    <mediatype major="MEDIATYPE_MPEG2_PES" sub="MEDIASUBTYPE_MPEG2_AUDIO"/>
    <mediatype major="MEDIATYPE_Audio" sub="MEDIASUBTYPE_MPEG2_AUDIO"/>
    <mediatype major="MEDIATYPE_DVD_ENCRYPTED_PACK" sub="MEDIASUBTYPE_DOLBY_AC3"/>
    <mediatype major="MEDIATYPE_MPEG2_PACK" sub="MEDIASUBTYPE_DOLBY_AC3"/>
    <mediatype major="MEDIATYPE_MPEG2_PES" sub="MEDIASUBTYPE_DOLBY_AC3"/>
    <mediatype major="MEDIATYPE_Audio" sub="MEDIASUBTYPE_DOLBY_AC3"/>
    <!--mediatype major="MEDIATYPE_Audio" sub="MEDIASUBTYPE_WAVE_DOLBY_AC3-->
    <mediatype major="MEDIATYPE_DVD_ENCRYPTED_PACK" sub="MEDIASUBTYPE_DTS"/>
    <mediatype major="MEDIATYPE_MPEG2_PACK" sub="MEDIASUBTYPE_DTS"/>
    <mediatype major="MEDIATYPE_MPEG2_PES" sub="MEDIASUBTYPE_DTS"/>
    <mediatype major="MEDIATYPE_Audio" sub="MEDIASUBTYPE_DTS"/>
    <mediatype major="MEDIATYPE_Audio" sub="MEDIASUBTYPE_WAVE_DTS"/>
    <mediatype major="MEDIATYPE_DVD_ENCRYPTED_PACK" sub="MEDIASUBTYPE_DVD_LPCM_AUDIO"/>
    <mediatype major="MEDIATYPE_MPEG2_PACK" sub="MEDIASUBTYPE_DVD_LPCM_AUDIO"/>
    <mediatype major="MEDIATYPE_MPEG2_PES" sub="MEDIASUBTYPE_DVD_LPCM_AUDIO"/>
    <mediatype major="MEDIATYPE_Audio" sub="MEDIASUBTYPE_DVD_LPCM_AUDIO"/>
    <mediatype major="MEDIATYPE_Audio" sub="MEDIASUBTYPE_HDMV_LPCM_AUDIO"/>
    <mediatype major="MEDIATYPE_DVD_ENCRYPTED_PACK" sub="MEDIASUBTYPE_AAC"/>
    <mediatype major="MEDIATYPE_MPEG2_PACK" sub="MEDIASUBTYPE_AAC"/>
    <mediatype major="MEDIATYPE_MPEG2_PES" sub="MEDIASUBTYPE_AAC"/>
    <mediatype major="MEDIATYPE_Audio" sub="MEDIASUBTYPE_AAC"/>
    <mediatype major="MEDIATYPE_DVD_ENCRYPTED_PACK" sub="MEDIASUBTYPE_MP4A"/>
    <mediatype major="MEDIATYPE_MPEG2_PACK" sub="MEDIASUBTYPE_MP4A"/>
    <mediatype major="MEDIATYPE_MPEG2_PES" sub="MEDIASUBTYPE_MP4A"/>
    <mediatype major="MEDIATYPE_Audio" sub="MEDIASUBTYPE_MP4A"/>
    <mediatype major="MEDIATYPE_DVD_ENCRYPTED_PACK" sub="MEDIASUBTYPE_mp4a"/>
    <mediatype major="MEDIATYPE_MPEG2_PACK" sub="MEDIASUBTYPE_mp4a"/>
    <mediatype major="MEDIATYPE_MPEG2_PES" sub="MEDIASUBTYPE_mp4a"/>
    <mediatype major="MEDIATYPE_Audio" sub="MEDIASUBTYPE_mp4a"/>
    <mediatype major="MEDIATYPE_DVD_ENCRYPTED_PACK" sub="{0000f521-0000-0010-8000-00aa00389b71}"/>
    <mediatype major="MEDIATYPE_MPEG2_PACK" sub="{0000f521-0000-0010-8000-00aa00389b71}"/>
    <mediatype major="MEDIATYPE_MPEG2_PES" sub="{0000f521-0000-0010-8000-00aa00389b71}"/>
    <mediatype major="MEDIATYPE_Audio" sub="{0000f521-0000-0010-8000-00aa00389b71}"/>
    <mediatype major="MEDIATYPE_DVD_ENCRYPTED_PACK" sub="{0000f522-0000-0010-8000-00aa00389b71}"/>
    <mediatype major="MEDIATYPE_MPEG2_PACK" sub="{0000f522-0000-0010-8000-00aa00389b71}"/>
    <mediatype major="MEDIATYPE_MPEG2_PES" sub="{0000f522-0000-0010-8000-00aa00389b71}"/>
    <mediatype major="MEDIATYPE_Audio" sub="{0000f522-0000-0010-8000-00aa00389b71}"/>
    <mediatype major="MEDIATYPE_Audio" sub="MEDIASUBTYPE_Vorbis2"/>
    <mediatype major="MEDIATYPE_Audio" sub="MEDIASUBTYPE_PCM_sowt"/>
    <mediatype major="MEDIATYPE_Audio" sub="MEDIASUBTYPE_PCM_twos"/>
    <mediatype major="MEDIATYPE_Audio" sub="MEDIASUBTYPE_PCM_in24"/>
    <mediatype major="MEDIATYPE_Audio" sub="{696E3234-0000-0010-8000-00AA00389B71}"/>
    <mediatype major="MEDIATYPE_Audio" sub="MEDIASUBTYPE_SAMR"/>
    <!--new-->
    <mediatype major="MEDIATYPE_DVD_ENCRYPTED_PACK" sub="{A7FB87AF-2D02-42FB-A4D4-05CD93843BDD}"/>
    <mediatype major="MEDIATYPE_MPEG2_PACK" sub="{A7FB87AF-2D02-42FB-A4D4-05CD93843BDD}"/>
    <mediatype major="MEDIATYPE_MPEG2_PES" sub="{A7FB87AF-2D02-42FB-A4D4-05CD93843BDD}"/>
    <mediatype major="MEDIATYPE_Audio" sub="{A7FB87AF-2D02-42FB-A4D4-05CD93843BDD}"/>
    <mediatype major="MEDIATYPE_DVD_ENCRYPTED_PACK" sub="{EB27CEC4-163E-4CA3-8B74-8E25F91B517E}"/>
    <mediatype major="MEDIATYPE_MPEG2_PACK" sub="{EB27CEC4-163E-4CA3-8B74-8E25F91B517E}"/>
    <mediatype major="MEDIATYPE_MPEG2_PES" sub="{EB27CEC4-163E-4CA3-8B74-8E25F91B517E}"/>
    <mediatype major="MEDIATYPE_Audio" sub="{EB27CEC4-163E-4CA3-8B74-8E25F91B517E}"/>
    <mediatype major="MEDIATYPE_Audio" sub="{000001ff-0000-0010-8000-00aa00389b71}"/>
    <mediatype major="MEDIATYPE_Audio" sub="{53544441-0000-0010-8000-00aa00389b71}"/>
    <mediatype major="MEDIATYPE_Audio" sub="MEDIASUBTYPE_AMR"/>
    <mediatype major="MEDIATYPE_Audio" sub="{62776173-0000-0010-8000-00aa00389b71}"/>
    <mediatype major="MEDIATYPE_Audio" sub="MEDIASUBTYPE_NELLYMOSER"/>
    <mediatype major="MEDIATYPE_Audio" sub="{454e4f4e-0000-0010-8000-00aa00389b71}"/>
    <mediatype major="MEDIATYPE_Audio" sub="MEDIASUBTYPE_PCM_RAW"/>
    <mediatype major="MEDIATYPE_Audio" sub="MEDIASUBTYPE_PCM_in32"/>
    <mediatype major="MEDIATYPE_Audio" sub="MEDIASUBTYPE_PCM_fl32"/>
    <mediatype major="MEDIATYPE_Audio" sub="MEDIASUBTYPE_PCM_fl64"/>
    <mediatype major="MEDIATYPE_Audio" sub="{696E3332-0000-0010-8000-00aa00389b71}"/>
    <mediatype major="MEDIATYPE_Audio" sub="{666c3332-0000-0010-8000-00aa00389b71}"/>
    <mediatype major="MEDIATYPE_Audio" sub="{666c3634-0000-0010-8000-00aa00389b71}"/>
    <mediatype major="MEDIATYPE_Audio" sub="MEDIASUBTYPE_IMA4"/>
    <mediatype major="MEDIATYPE_Audio" sub="{00005346-0000-0010-8000-00aa00389b71}"/>
    <mediatype major="MEDIATYPE_Audio" sub="MEDIASUBTYPE_14_4"/>
    <mediatype major="MEDIATYPE_Audio" sub="MEDIASUBTYPE_28_8"/>
    <mediatype major="MEDIATYPE_Audio" sub="MEDIASUBTYPE_ATRC"/>
    <mediatype major="MEDIATYPE_Audio" sub="MEDIASUBTYPE_COOK"/>
    <mediatype major="MEDIATYPE_Audio" sub="MEDIASUBTYPE_DNET"/>
    <mediatype major="MEDIATYPE_Audio" sub="MEDIASUBTYPE_SIPR"/>
    <mediatype major="MEDIATYPE_Audio" sub="MEDIASUBTYPE_RAAC"/>
    <mediatype major="MEDIATYPE_Audio" sub="MEDIASUBTYPE_RACP"/>
    <mediatype major="MEDIATYPE_Audio" sub="MEDIASUBTYPE_FLAC"/>
    <mediatype major="MEDIATYPE_Audio" sub="MEDIASUBTYPE_FLAC_FRAMED"/>
  </codecs>

  <codecs
    enable="1" priority="11"
    name="Intel(R) Media SDK H.264 Decoder"
    pathflag="file"
    path="h264_dec_filter.dll"
    category="dsfilter"
    type="vdec"
    clsid="{CCCE52FD-02CB-482C-AC81-1E55EF1D61EE}" >
    <mediatype major="MEDIATYPE_Video" sub="MEDIASUBTYPE_H264"/>
    <mediatype major="MEDIATYPE_Video" sub="MEDIASUBTYPE_AVC1"/>
  </codecs>

</CodecsInfo>
